virgo_modules/__init__.py
virgo_modules/src/__init__.py
virgo_modules/src/aws_utils.py
virgo_modules/src/backtester.py
virgo_modules/src/hmm_utils.py
virgo_modules/src/pull_artifacts.py
virgo_modules/src/re_utils.py
virgo_modules/src/ticketer_source.py
virgo_modules/src/transformer_utils.py
virgo_modules/src/edge_utils/__init__.py
virgo_modules/src/edge_utils/conformal_utils.py
virgo_modules/src/edge_utils/edge_utils.py
virgo_modules/src/edge_utils/feature_selection.py
virgo_modules/src/edge_utils/shap_utils.py
virgo_modules/src/edge_utils/stack_model.py
virgo_modules/src/market/__init__.py
virgo_modules/src/market/market_tools.py
virgo_modules/src/markowitz/__init__.py
virgo_modules/src/markowitz/markowitz_utils.py
virgo_modules-0.9.0.dist-info/licenses/LICENSE
virgo_modules-0.9.0.dist-info/METADATA
virgo_modules-0.9.0.dist-info/WHEEL
virgo_modules-0.9.0.dist-info/top_level.txt
virgo_modules-0.9.0.dist-info/RECORD
