Metadata-Version: 2.4
Name: virgo_modules
Version: 0.9.0
Summary: data processing and statistical modeling using stock market data
Home-page: https://github.com/miguelmayhem92/virgo_module
Author: Miguel Mayhuire
Author-email: miguelmayhem92@gmail.com
License: MIT
Classifier: License :: OSI Approved :: MIT License
Classifier: Programming Language :: Python :: 3.9
Classifier: Operating System :: OS Independent
Requires-Python: >=3.9
License-File: LICENSE
Provides-Extra: dev
Requires-Dist: pytest>=7.0; extra == "dev"
Dynamic: author
Dynamic: author-email
Dynamic: classifier
Dynamic: description
Dynamic: description-content-type
Dynamic: home-page
Dynamic: license
Dynamic: license-file
Dynamic: provides-extra
Dynamic: requires-python
Dynamic: summary
